MANIFEST.in
setup.py
Pixelmon/Biomes_to_Pokemon.json
Pixelmon/Pokemon_to_Biomes.json
Pixelmon/__init__.py
Pixelmon/better_drops.json
Pixelmon/biome_config.json
Pixelmon/bounty.py
Pixelmon/drops.py
Pixelmon/forage.json
Pixelmon/forage.py
Pixelmon/new_spawning.py
Pixelmon/pixelmon_spawning.py
Pixelmon/pokedrops.json
Pixelmon/spawning/Abomasnow.set.json
Pixelmon/spawning/Abra.set.json
Pixelmon/spawning/Absol.set.json
Pixelmon/spawning/Accelgor.set.json
Pixelmon/spawning/Aggron.set.json
Pixelmon/spawning/Aipom.set.json
Pixelmon/spawning/Alakazam.set.json
Pixelmon/spawning/Alomomola.set.json
Pixelmon/spawning/Altaria.set.json
Pixelmon/spawning/Ambipom.set.json
Pixelmon/spawning/Amoonguss.set.json
Pixelmon/spawning/Arbok.set.json
Pixelmon/spawning/Ariados.set.json
Pixelmon/spawning/Aron.set.json
Pixelmon/spawning/Audino.set.json
Pixelmon/spawning/Axew.set.json
Pixelmon/spawning/Azelf.set.json
Pixelmon/spawning/Azumarill.set.json
Pixelmon/spawning/Azurill.set.json
Pixelmon/spawning/Bagon.set.json
Pixelmon/spawning/Baltoy.set.json
Pixelmon/spawning/Banette.set.json
Pixelmon/spawning/Barboach.set.json
Pixelmon/spawning/Basculin.set.json
Pixelmon/spawning/Bayleef.set.json
Pixelmon/spawning/Beartic.set.json
Pixelmon/spawning/Beautifly.set.json
Pixelmon/spawning/Beedrill.set.json
Pixelmon/spawning/Beheeyem.set.json
Pixelmon/spawning/Beldum.set.json
Pixelmon/spawning/Bellossom.set.json
Pixelmon/spawning/Bellsprout.set.json
Pixelmon/spawning/Bergmite.set.json
Pixelmon/spawning/Bibarel.set.json
Pixelmon/spawning/Bidoof.set.json
Pixelmon/spawning/Binacle.set.json
Pixelmon/spawning/Bisharp.set.json
Pixelmon/spawning/Blastoise.set.json
Pixelmon/spawning/Blaziken.set.json
Pixelmon/spawning/Blitzle.set.json
Pixelmon/spawning/Boldore.set.json
Pixelmon/spawning/Bonsly.set.json
Pixelmon/spawning/Bouffalant.set.json
Pixelmon/spawning/Braixen.set.json
Pixelmon/spawning/Braviary.set.json
Pixelmon/spawning/Breloom.set.json
Pixelmon/spawning/Bronzong.set.json
pixelmon.egg-info/PKG-INFO
pixelmon.egg-info/SOURCES.txt
pixelmon.egg-info/dependency_links.txt
pixelmon.egg-info/not-zip-safe
pixelmon.egg-info/top_level.txt