Metadata-Version: 1.0
Name: pixelmon
Version: 0.1
Summary: Pixemon Util Commands
Home-page: https://github.com/77Wertfuzzy77/Pixelmon
Author: Nikolai Narma
Author-email: UNKNOWN
License: UNKNOWN
Platform: UNKNOWN
